graph_judge/__init__.py
graph_judge/result.py
graph_judge-0.0.6.dist-info/LICENSE.md
graph_judge-0.0.6.dist-info/METADATA
graph_judge-0.0.6.dist-info/WHEEL
graph_judge-0.0.6.dist-info/top_level.txt
graph_judge-0.0.6.dist-info/RECORD
