Metadata-Version: 2.1
Name: graph-judge
Version: 0.0.6
Summary: TODO edit me
Home-page: https://github.com/spencer-hanson/GraphJudge
Author: Spencer Hanson
Classifier: Programming Language :: Python :: 3
License-File: LICENSE.md
